amplitude/__init__.py
amplitude/client.py
amplitude/config.py
amplitude/constants.py
amplitude/event.py
amplitude/exception.py
amplitude/http_client.py
amplitude/plugin.py
amplitude/processor.py
amplitude/storage.py
amplitude/timeline.py
amplitude/utils.py
amplitude/worker.py
amplitude_analytics-1.2.0.dist-info/LICENSE
amplitude_analytics-1.2.0.dist-info/METADATA
amplitude_analytics-1.2.0.dist-info/WHEEL
amplitude_analytics-1.2.0.dist-info/top_level.txt
amplitude_analytics-1.2.0.dist-info/RECORD
