Metadata-Version: 2.1
Name: amplitude-analytics
Version: 1.2.0
Summary: The official Amplitude backend Python SDK for server-side instrumentation.
Home-page: https://github.com/amplitude/Amplitude-Python
Author: Amplitude Inc.
Author-email: sdk.dev@amplitude.com
License: MIT License
Project-URL: Bug Reports, https://github.com/amplitude/Amplitude-Python/issues
Project-URL: Source, https://github.com/amplitude/Amplitude-Python
Project-URL: Developer Doc, https://docs.developers.amplitude.com/data/sdks/python/
Keywords: amplitude,python,backend
Classifier: Development Status :: 5 - Production/Stable
Classifier: Intended Audience :: Developers
Classifier: License :: OSI Approved :: MIT License
Classifier: Programming Language :: Python :: 3
Classifier: Programming Language :: Python :: 3.6
Classifier: Programming Language :: Python :: 3.7
Classifier: Programming Language :: Python :: 3.8
Classifier: Programming Language :: Python :: 3.9
Classifier: Programming Language :: Python :: 3.10
Requires-Python: >=3.6, <4
License-File: LICENSE
